archive_md_urls/__init__.py
archive_md_urls/cli.py
archive_md_urls/gather_snapshots.py
archive_md_urls/scan_md.py
archive_md_urls/update_files.py
archive_md_urls-0.0.7.post1.dist-info/METADATA
archive_md_urls-0.0.7.post1.dist-info/WHEEL
archive_md_urls-0.0.7.post1.dist-info/entry_points.txt
archive_md_urls-0.0.7.post1.dist-info/licenses/LICENSE
archive_md_urls-0.0.7.post1.dist-info/RECORD
