Metadata-Version: 2.1
Name: archive-md-urls
Version: 0.0.7.post1
Summary: Turn URLs in Markdown files into archive.org snapshots
Project-URL: Homepage, https://github.com/sbaack/archive-md-urls
Project-URL: Bug Tracker, https://github.com/sbaack/archive-md-urls/issues
Author: Stefan Baack
License: 
License-File: LICENSE
Classifier: License :: OSI Approved :: GNU General Public License v3 or later (GPLv3+)
Classifier: Operating System :: OS Independent
Classifier: Programming Language :: Python :: 3
Requires-Python: >=3.9
Requires-Dist: beautifulsoup4>=4
Requires-Dist: httpx<1.0,>=0.18
Requires-Dist: markdown>=3.3
Requires-Dist: python-dateutil>=2.8
Requires-Dist: tenacity>=8
